{
  "creds": {
    "noiseKey": {
      "private": {
        "type": "Buffer",
        "data": "EBBGsMg9utI3FSjayM4LurKlWuzIQbTQF4UvjCVGelo="
      },
      "public": {
        "type": "Buffer",
        "data": "qQ9ppKP45efcBX+4znjOaR9DSrSnhqy1+kRLuQsNZiM="
      }
    },
    "signedIdentityKey": {
      "private": {
        "type": "Buffer",
        "data": "8OsqeOyJ2ei9PkK+eDAXYdmAJdo5lSs+o48aiSeRPU0="
      },
      "public": {
        "type": "Buffer",
        "data": "Q+BdjQ0cbtQVnFhNowT85gy+4m0wxWIc05deUo/5fWw="
      }
    },
    "signedPreKey": {
      "keyPair": {
        "private": {
          "type": "Buffer",
          "data": "gNTLeiGfYsMKXnIq3RM0j3P/elBvB+SMEdihpVhuhW0="
        },
        "public": {
          "type": "Buffer",
          "data": "237Fo1tnji50E31Q7YLsWnJNd21QtsPl+rHH1saP+2Q="
        }
      },
      "signature": {
        "type": "Buffer",
        "data": "/hR2O2LkAO06eevyfqr3yKiaO2SCeQvm1R0ZDtdlbw1N2OlCN9Fy5hacxRNMmmRVkoArnLtYpQImxsULlZ6RAw=="
      },
      "keyId": 1
    },
    "registrationId": 251,
    "advSecretKey": "4wziAPf1VS2WOX6BcQwMSIqj9o8kNUeIOUNr28IIbqU=",
    "processedHistoryMessages": [
      {
        "key": {
          "remoteJid": "212621325510@s.whatsapp.net",
          "fromMe": true,
          "id": "3AC9E1CE6A78998BED8E"
        },
        "messageTimestamp": 1707014826
      },
      {
        "key": {
          "remoteJid": "212621325510@s.whatsapp.net",
          "fromMe": true,
          "id": "3A32DC221333BC0AE2C1"
        },
        "messageTimestamp": 1707014827
      }
    ],
    "nextPreKeyId": 31,
    "firstUnuploadedPreKeyId": 31,
    "accountSettings": {
      "unarchiveChats": false
    },
    "account": {
      "details": "CJWP3JIPEKT1+60GGAUgACgA",
      "accountSignatureKey": "BfdZWwsHBxb92FhgqX+b7jDlZ7qvgTh/zWO8+C6dFg8=",
      "accountSignature": "BL06Z0XCtBV+0bDZq11Xd7iguztOJofkEo3n0AunDbqrSolJcQ+GiIVhqoRGFJeZUBoE0KoCgVGY6LblsUlCCQ==",
      "deviceSignature": "5ruk5/VlDdu2Fb95xV+v/rb7/34Z7FPRUatTp8KlYarL+2xPycJPv0UIuTUtAiyfa/Hks8V0thMQzUjA/WbjDA=="
    },
    "me": {
      "id": "212621325510:68@s.whatsapp.net",
      "name": "Ilys Bro"
    },
    "signalIdentities": [
      {
        "identifier": {
          "name": "212621325510:68@s.whatsapp.net",
          "deviceId": 0
        },
        "identifierKey": {
          "type": "Buffer",
          "data": "BQX3WVsLBwcW/dhYYKl/m+4w5We6r4E4f81jvPgunRYP"
        }
      }
    ],
    "platform": "iphone",
    "lastAccountSyncTimestamp": 1707014822,
    "myAppStateKeyId": "AAAAAE2h"
  },
  "keys": {
    "preKeys": {
      "1": {
        "private": {
          "type": "Buffer",
          "data": "CDtWq97F5raE1ehoYuT2/IZMY1Dz5p0DI5ogegbWr0A="
        },
        "public": {
          "type": "Buffer",
          "data": "8LMbhT4Ap9Fek/AUJI08XUd0b867Rzk+m3k4DDkfX38="
        }
      },
      "2": {
        "private": {
          "type": "Buffer",
          "data": "UIaglVs5Hxjp7v+uPYpB8yZI/x12fCCPZ8lwtTY4S3U="
        },
        "public": {
          "type": "Buffer",
          "data": "7oUFaWFA1VK9zVTScOYOblk6gFmPsem6SYU1Utj7nj4="
        }
      },
      "3": {
        "private": {
          "type": "Buffer",
          "data": "WBneIkSI6bj5P1Y6e0q3/LCdORFoQSGXPGLTR+zN924="
        },
        "public": {
          "type": "Buffer",
          "data": "iqY/0yidbM2EjiXKLZEYIr6geHr3XOLyLsa31R3FwXw="
        }
      },
      "4": {
        "private": {
          "type": "Buffer",
          "data": "OHlI7E8ZDvKhH7Ku+b/OnYcW59dLQm3kO9UXGZZM52I="
        },
        "public": {
          "type": "Buffer",
          "data": "l63KcNcXDcCjGFQB/qFDAC8cDrv53R7wkGRme+s4WXI="
        }
      },
      "5": {
        "private": {
          "type": "Buffer",
          "data": "AJdd2pM3oiLoFpd6I3HedT9T5wkEcIjLSL6tpuVIE0I="
        },
        "public": {
          "type": "Buffer",
          "data": "P3Nwg95yc59lfUK/2uFP0554k2I2fp9RcOmiF+IW4Us="
        }
      },
      "6": {
        "private": {
          "type": "Buffer",
          "data": "kFUlidjssOvGK6jfgmj2pp0Y33ZDQzM6fwBxNvX3v0E="
        },
        "public": {
          "type": "Buffer",
          "data": "vcxaWOgmByOpQv0RY4LjoQsncN9zPHymepLn+RFJHz0="
        }
      },
      "7": {
        "private": {
          "type": "Buffer",
          "data": "2LYbzGbw5xLFwFAeS2f0J4xTjjjoqmpnEJov/5cHO1Q="
        },
        "public": {
          "type": "Buffer",
          "data": "ibRBLC5/3eXbePf0yvAq/VMl3um/WQltbn1jSi+usHU="
        }
      },
      "8": {
        "private": {
          "type": "Buffer",
          "data": "OLkm+DXEGCWVnb13n5CDaDuhWex6b6Eyt5KIvBvT0HM="
        },
        "public": {
          "type": "Buffer",
          "data": "PagKo6XWfDyGPscXl0FgQsJAvOd/uh0vXfFOlPf8clM="
        }
      },
      "9": {
        "private": {
          "type": "Buffer",
          "data": "qA04zA32OFKtuS+cDTpJCn55jtzWOuVTI4rTQSvLUlw="
        },
        "public": {
          "type": "Buffer",
          "data": "m4KwvKMP9SWeIzqnPlHUYXXmC/5L0pXzLrGUVKqV93A="
        }
      },
      "10": {
        "private": {
          "type": "Buffer",
          "data": "oNe0Xi5EHNdcA9UNuCT7uN5MhLwQlxLXjmmDG8/sfHE="
        },
        "public": {
          "type": "Buffer",
          "data": "4Hwt+A/vmmU0TBb5iXSjB33rUhWomt+M6rixolpA63U="
        }
      },
      "11": {
        "private": {
          "type": "Buffer",
          "data": "wJ1X6jjYtPmO/l/SVg7Kx+pB8ptKFond/ztsj8y6kXQ="
        },
        "public": {
          "type": "Buffer",
          "data": "P5ZtdNmHLfkndi+kRxcgYNoBaK6iKgVHY/LGIIasASE="
        }
      },
      "12": {
        "private": {
          "type": "Buffer",
          "data": "qH2szRgtebi/8AKWpjTS8Iu16kt6zvzF7vOmwhwYOGI="
        },
        "public": {
          "type": "Buffer",
          "data": "v6EaOIWblxy+EcpCA9TyERFcHMR2/hA0pbG6KeAUO18="
        }
      },
      "13": {
        "private": {
          "type": "Buffer",
          "data": "WFU4k6mBbPOUlZBUDsy5BUdhFBJffCvigItnmD08Ak8="
        },
        "public": {
          "type": "Buffer",
          "data": "EGd46b1qnbPKxYVHEBpRnc5vmH7FikMfnHGh0OdYqQ8="
        }
      },
      "14": {
        "private": {
          "type": "Buffer",
          "data": "uCHSOPTxNz7jRJHd4WHm0qTxGEDEfg8T+8VEzUSmzFI="
        },
        "public": {
          "type": "Buffer",
          "data": "sBdG17J8joEuvWtz5JmZRkg6gFys7T/S08vFOsbGggA="
        }
      },
      "15": {
        "private": {
          "type": "Buffer",
          "data": "CN91F8cW8YJbkYv7iccSnTdAYzAan5UzlTQEiH6LSmc="
        },
        "public": {
          "type": "Buffer",
          "data": "0b9G2mcPJkDjiA/paXAm9EB+S95ru9R8BtjZPZTPmFw="
        }
      },
      "16": {
        "private": {
          "type": "Buffer",
          "data": "gPF+BpIf+fYoqHJayB+WnTagMY4Xj1x+rcY5NnwMCE8="
        },
        "public": {
          "type": "Buffer",
          "data": "J/bXZMwKq8KzmstD2QxiDQHSAswMqub9tzYxhceoF24="
        }
      },
      "17": {
        "private": {
          "type": "Buffer",
          "data": "8L5bQI7F/IGBG39frmgjmD3RvrlvCAQYFxd64uNG/2E="
        },
        "public": {
          "type": "Buffer",
          "data": "2kzz1rO/S7kq2uGG19lOJep73csSmBVV12nhdRDO+EU="
        }
      },
      "18": {
        "private": {
          "type": "Buffer",
          "data": "mMl5Lu8VAmAP0RYMZjzHDgIv61OllCnpSMi6pwrEJ2M="
        },
        "public": {
          "type": "Buffer",
          "data": "GdhAzE0qec5WZmmP0cIT3Emzjs8WQ3pXvnXruLXOK2A="
        }
      },
      "19": {
        "private": {
          "type": "Buffer",
          "data": "+FJXJz+t8Mb/a9p15eNxy9FZn3xnZo1zkjJfS9URLls="
        },
        "public": {
          "type": "Buffer",
          "data": "48YRMmoJlhxFpJHzw6jn8/3faVyJI20PWYjS8RQKuXw="
        }
      },
      "20": {
        "private": {
          "type": "Buffer",
          "data": "KBLlCPG2aDOXl4fznCFd9h03DQPstsSORQw3QVPZWng="
        },
        "public": {
          "type": "Buffer",
          "data": "zU4bZ7HgifBNEEgVydfJiEPBVK636Bs12SLYuxroqXo="
        }
      },
      "21": {
        "private": {
          "type": "Buffer",
          "data": "mDYShg5kphsprI+s7G/7XqmOH5K8AgW1xEvBvGttU3s="
        },
        "public": {
          "type": "Buffer",
          "data": "g2q9/pGVwJ7dOFrxLIEvYxgED0QC/R9Kq0FyftnNLTI="
        }
      },
      "22": {
        "private": {
          "type": "Buffer",
          "data": "CAz3CG1h5hUiZPCa567pXxxL2NByL14XerQwUbET5Hk="
        },
        "public": {
          "type": "Buffer",
          "data": "ikf++kXgRyvI4P3UPjJ5LkfAngRMxvUJUzzBxzjYcHs="
        }
      },
      "23": {
        "private": {
          "type": "Buffer",
          "data": "aGXvoQfJk4QwfkAikt4yzPGtlfWQ4yGrmRd3uVHow1g="
        },
        "public": {
          "type": "Buffer",
          "data": "Y9Rnt00/O8rgzAyeNBTa8Dpy/ipD++ZaOAhy5bYPmXc="
        }
      },
      "24": null,
      "25": {
        "private": {
          "type": "Buffer",
          "data": "aIAuiqzQTADqwWi3ezNwxxtml0FMX3yoIeNu1DTiXnY="
        },
        "public": {
          "type": "Buffer",
          "data": "iy+PHB3BLPJhLKHAhoG/gx0hDBR5626nST6L0FiWCCA="
        }
      },
      "26": {
        "private": {
          "type": "Buffer",
          "data": "UGTCK9lk9yvLwzjVsT3mROlvRBaD2lh+avPib0LYyUU="
        },
        "public": {
          "type": "Buffer",
          "data": "WcuZuEyWL519CHGJslegW3kgnTKxtlDyDlRaLiAB22c="
        }
      },
      "27": {
        "private": {
          "type": "Buffer",
          "data": "yDMfCE5JnduZiDSoSbsqTbEqvsJo5V6T/nxbrCJC1ng="
        },
        "public": {
          "type": "Buffer",
          "data": "sIXNnz9yFTcdg1PedXykgqi0IOklFSapCfNKRPm/vko="
        }
      },
      "28": {
        "private": {
          "type": "Buffer",
          "data": "kMqGSk4BGfvvLYM/uj8WEoTMTmqNRmRhctj3q2rlSUU="
        },
        "public": {
          "type": "Buffer",
          "data": "SmSSZ4hpMdWJGI/glCfrvFbjfZBMbu/SH3kiiRxr+xc="
        }
      },
      "29": {
        "private": {
          "type": "Buffer",
          "data": "sMv2HaW1C05gbM5u4ye+uWbkIU2TWpPFY6N1KqJIPlI="
        },
        "public": {
          "type": "Buffer",
          "data": "aSs403gsOF0/0Zyo1eI/zekViVhFRbkCsuTZ52fYngo="
        }
      },
      "30": {
        "private": {
          "type": "Buffer",
          "data": "KHar9KUErTMsnqMjKK3WbOqiy6pOvV0gwAIYf6MEp2Y="
        },
        "public": {
          "type": "Buffer",
          "data": "e9eFgPJLRdi0Uge36mnySap+ds6F/jXv1Ng6WYv1ymE="
        }
      }
    },
    "sessions": {
      "212621325510.0": {
        "_sessions": {
          "BVC/Ba+XohLHo5kLW1cXE7nByLcgrJoUqqXJ6fnRkpYg": {
            "registrationId": 1136749988,
            "currentRatchet": {
              "ephemeralKeyPair": {
                "pubKey": "BTtudWE4/h/9vYt3eR/U13oHnVt3ppSDh828QYacAyAh",
                "privKey": "EGXaBzB494xYucryVx1hV8Bio6yXjvGLaOJ37p6TjFQ="
              },
              "lastRemoteEphemeralKey": "BQfS9sdf7NhN4UOYpYxk5yFSLiWaEw2TTP910bAe37dn",
              "previousCounter": 0,
              "rootKey": "ANw2a5xlIWkEXc+NIP0XIOcwb51EWyZ94Y9Kzf/9qoE="
            },
            "indexInfo": {
              "baseKey": "BVC/Ba+XohLHo5kLW1cXE7nByLcgrJoUqqXJ6fnRkpYg",
              "baseKeyType": 2,
              "closed": -1,
              "used": 1707014823925,
              "created": 1707014823925,
              "remoteIdentityKey": "BQX3WVsLBwcW/dhYYKl/m+4w5We6r4E4f81jvPgunRYP"
            },
            "_chains": {
              "BQfS9sdf7NhN4UOYpYxk5yFSLiWaEw2TTP910bAe37dn": {
                "chainKey": {
                  "counter": 5,
                  "key": "P8UukwXh3i6MC7ujU7lJGvSwccRUIX2896bQaDripYk="
                },
                "chainType": 2,
                "messageKeys": {}
              },
              "BTtudWE4/h/9vYt3eR/U13oHnVt3ppSDh828QYacAyAh": {
                "chainKey": {
                  "counter": 3,
                  "key": "dAJiu+IqNPU5ZCARdKoBbcznlHlmZjkwccrAfuIx3tw="
                },
                "chainType": 1,
                "messageKeys": {}
              }
            }
          }
        },
        "version": "v1"
      },
      "212621325510:65.0": {
        "_sessions": {
          "Bc/kFGNRtueBe0F99iI/0gUVuVJtWyhkgg7LnPNiubxa": {
            "registrationId": 14654,
            "currentRatchet": {
              "ephemeralKeyPair": {
                "pubKey": "BQrKQabE2EadUGfTNPfIYeZGSntooL1Qhav5ZfICRIN0",
                "privKey": "uMqCLp4x8wKIfPBtWZRamyye559Fra3M4u1yiYmYGXg="
              },
              "lastRemoteEphemeralKey": "BYQ4EZQp/rFL45fcsRWkHFBa4P25bgSHWUWwjoQGMX8y",
              "previousCounter": 0,
              "rootKey": "AWVA3TDp3PNyL02Y8nsLrgBRZ8i0MX5g+9wXViz/l0c="
            },
            "indexInfo": {
              "baseKey": "Bc/kFGNRtueBe0F99iI/0gUVuVJtWyhkgg7LnPNiubxa",
              "baseKeyType": 1,
              "closed": -1,
              "used": 1707014834357,
              "created": 1707014834357,
              "remoteIdentityKey": "BfqEc8d5eQ/OXPv4yLCGir8J8qk9uOtP92s2y3eamchb"
            },
            "_chains": {
              "BQrKQabE2EadUGfTNPfIYeZGSntooL1Qhav5ZfICRIN0": {
                "chainKey": {
                  "counter": 1,
                  "key": "Ffd79tAEsBrOz3L0iGuiwAH2vBHDkGa7lufpTrRdMbs="
                },
                "chainType": 1,
                "messageKeys": {}
              }
            },
            "pendingPreKey": {
              "signedKeyId": 1,
              "baseKey": "Bc/kFGNRtueBe0F99iI/0gUVuVJtWyhkgg7LnPNiubxa",
              "preKeyId": 192
            }
          }
        },
        "version": "v1"
      }
    },
    "appStateSyncKeys": {
      "AAAAAE2j": {
        "keyData": "n7p6ShW+14N4P6UqNUphLss27NwHa2hBImyxRTx1p9Q=",
        "fingerprint": {
          "rawId": 4065789845,
          "currentIndex": 4,
          "deviceIndexes": [
            4,
            0,
            2
          ]
        },
        "timestamp": "1707014675385"
      },
      "AAAAAE2d": {
        "keyData": "nuz02UneLPrXIOS11NcTv2sG5bNfROPgiMxAen9E76U=",
        "fingerprint": {
          "rawId": 4065789845,
          "currentIndex": 1,
          "deviceIndexes": [
            0,
            1
          ]
        },
        "timestamp": "1706878898916"
      },
      "AAAAAE2f": {
        "keyData": "TJj4R/340pS9OY4FPKwF/q5cKaJ1mpcXznZ7jCcGz0Q=",
        "fingerprint": {
          "rawId": 4065789845,
          "currentIndex": 2,
          "deviceIndexes": [
            2,
            1,
            0
          ]
        },
        "timestamp": "1706999184036"
      },
      "AAAAAE2h": {
        "keyData": "E7TFLvyuBGJL0ghm4hQWL10rWWcfLfLoFd5RCpVleGY=",
        "fingerprint": {
          "rawId": 4065789845,
          "currentIndex": 3,
          "deviceIndexes": [
            3,
            0,
            2
          ]
        },
        "timestamp": "1707003095552"
      }
    }
  }
}
